{
	"activate InstName.{LitOperationName({ArgumentList})}": {
		"prefix": "activate",
		"body": [
			"activate '$1'.$2($3)"
		],
		"description": "Calls an operation on a component instance."
	},
	"activate/list InstName.{LitOperationName({ArgumentList})}": {
		"prefix": "activate/list",
		"body": [
			"activate/list '$1'.$2($3)"
		],
		"description": "Calls an operation on a component instance."
	},
	"activate/sync InstName.{LitOperationName({ArgumentList})}": {
		"prefix": "activate/sync",
		"body": [
			"activate/sync '$1'.$2($3)"
		],
		"description": "Calls an operation on a component instance."
	},
	"activate/async InstName.{LitOperationName({ArgumentList})}": {
		"prefix": "activate/async",
		"body": [
			"activate/async '$1'.$2($3)"
		],
		"description": "Calls an operation on a component instance."
	},
	"activate/stateless InstName.{LitOperationName({ArgumentList})}": {
		"prefix": "activate/stateless",
		"body": [
			"activate/stateless '$1'.$2($3)"
		],
		"description": "Calls an operation on a component instance."
	},
	"addmonths Months, Date, {ReferenceDate}": {
		"prefix": "addmonths",
		"body": [
			"addmonths '$1','$2','$3'"
		],
		"description": "Adds the specified number of months to the date, storing the result of the calculation in $result."
	},
	"apexit": {
		"prefix": "apexit",
		"body": [
			"apexit"
		],
		"description": "Ends the application session immediately."
	},
	"apstart": {
		"prefix": "apstart",
		"body": [
			"apstart"
		],
		"description": "Pass control of the application to the component manager."
	},
	"askmess 'MessageText{~MessageTitle}', {Replies}": {
		"prefix": "askmess",
		"body": [
			"askmess '$1', '$2'"
		],
		"description": "Display a message and wait for the user's response."
	},
	"askmess/nobeep 'MessageText{~MessageTitle}', {Replies}": {
		"prefix": "askmess/nobeep",
		"body": [
			"askmess/nobeep '$1', '$2'"
		],
		"description": "Display a message and wait for the user's response."
	},
	"askmess/question 'MessageText{~MessageTitle}', {Replies}": {
		"prefix": "askmess/question",
		"body": [
			"askmess/question '$1', '$2'"
		],
		"description": "Display a message and wait for the user's response."
	},
	"askmess/info 'MessageText{~MessageTitle}', {Replies}": {
		"prefix": "askmess/info",
		"body": [
			"askmess/info '$1', '$2'"
		],
		"description": "Display a message and wait for the user's response."
	},
	"askmess/warning 'MessageText{~MessageTitle}', {Replies}": {
		"prefix": "askmess/warning",
		"body": [
			"askmess/warning '$1', '$2'"
		],
		"description": "Display a message and wait for the user's response."
	},
	"askmess/error 'MessageText{~MessageTitle}', {Replies}": {
		"prefix": "askmess/error",
		"body": [
			"askmess/error '$1', '$2'"
		],
		"description": "Display a message and wait for the user's response."
	},
	"blockdata": {
		"prefix": "blockdata",
		"body": [
			"blockdata"
		],
		"description": "Defines a constant block of text."
	},
	"call {Library::}LitFunctionName {(ArgumentList)}": {
		"prefix": "call",
		"body": [
			"call $1"
		],
		"description": "Execute the specified function or global ProcScript."
	},
	"putitem list, index, element": {
		"prefix": "putitem",
		"body": [
			"putitem '$1', '$2', '$3'"
		],
		"description": "Add or replace an item in a list."
	},
	"putitem/id list, id, element": {
		"prefix": "putitem/id",
		"body": [
			"putitem/id '$1', '$2', '$3'"
		],
		"description": "Add or replace an item in a list."
	},
	"putitem/id/case list, id, element": {
		"prefix": "putitem/id/case",
		"body": [
			"putitem/id/case '$1', '$2', '$3'"
		],
		"description": "Add or replace an item in a list."
	}
}